django_table_sort/__init__.py
django_table_sort/columns.py
django_table_sort/helpers.py
django_table_sort/static/django_table_sort.css
django_table_sort/table.py
django_table_sort/templates/django_table_sort/table.html
django_table_sort-0.6.0.dist-info/LICENSE
django_table_sort-0.6.0.dist-info/METADATA
django_table_sort-0.6.0.dist-info/WHEEL
django_table_sort-0.6.0.dist-info/RECORD
