Metadata-Version: 2.1
Name: django-table-sort
Version: 0.6.0
Summary: Create tables with sorting links on the headers in Django templates.
Home-page: https://github.com/TheRealVizard/django-table-sort
License: BSD-3-Clause
Keywords: django,table,sort,templates
Author: TheRealVizard
Author-email: vizard@divineslns.com
Requires-Python: >=3.9
Classifier: Environment :: Web Environment
Classifier: Framework :: Django
Classifier: Framework :: Django :: 3.2
Classifier: Framework :: Django :: 4.0
Classifier: Framework :: Django :: 4.1
Classifier: Framework :: Django :: 4.2
Classifier: Intended Audience :: Developers
Classifier: License :: OSI Approved :: BSD License
Classifier: License :: OSI Approved :: MIT License
Classifier: Operating System :: OS Independent
Classifier: Programming Language :: Python
Classifier: Programming Language :: Python :: 3
Classifier: Programming Language :: Python :: 3.9
Classifier: Programming Language :: Python :: 3.10
Classifier: Programming Language :: Python :: 3.11
Classifier: Programming Language :: Python :: 3 :: Only
Classifier: Programming Language :: Python :: 3.12
Classifier: Topic :: Software Development :: Libraries :: Python Modules
Requires-Dist: django (>=3.2)
Project-URL: Documentation, https://django-table-sort.readthedocs.io/en/latest/
Project-URL: Repository, https://github.com/TheRealVizard/django-table-sort
